lemmy/__init__.py
lemmy/lemmatizer.py
lemmy/version.py
lemmy/pipe/__init__.py
lemmy/pipe/component.py
lemmy/rules/__init__.py
lemmy/rules/da.py
lemmy/rules/sv.py
lemmy-2.1.0.dist-info/LICENSE
lemmy-2.1.0.dist-info/METADATA
lemmy-2.1.0.dist-info/WHEEL
lemmy-2.1.0.dist-info/top_level.txt
lemmy-2.1.0.dist-info/RECORD
