Metadata-Version: 2.1
Name: lemmy
Version: 2.1.0
Summary: Lemmatizer for Danish
Home-page: https://github.com/sorenlind/lemmy/
Author: Soren Lind Kristiansen
Author-email: sorenlind@mac.com
License: UNKNOWN
Keywords: nlp lemma lemmatizer lemmatiser danish spacy
Platform: UNKNOWN
Classifier: Development Status :: 3 - Alpha
Classifier: Intended Audience :: Developers
Classifier: Intended Audience :: Science/Research
Classifier: License :: OSI Approved :: MIT License
Classifier: Natural Language :: Danish
Classifier: Operating System :: OS Independent
Classifier: Programming Language :: Python :: 2.7
Classifier: Programming Language :: Python :: 3.6
Classifier: Topic :: Text Processing :: Linguistic
Provides-Extra: dev
Requires-Dist: pandas ; extra == 'dev'
Requires-Dist: jupyter ; extra == 'dev'
Requires-Dist: unicodecsv ; extra == 'dev'
Requires-Dist: bs4 ; extra == 'dev'
Requires-Dist: tqdm ; extra == 'dev'
Requires-Dist: regex ; extra == 'dev'
Requires-Dist: spacy ; extra == 'dev'
Requires-Dist: pylint ; extra == 'dev'
Requires-Dist: pycodestyle ; extra == 'dev'
Requires-Dist: pydocstyle ; extra == 'dev'
Requires-Dist: yapf ; extra == 'dev'
Requires-Dist: pytest ; extra == 'dev'
Requires-Dist: tox ; extra == 'dev'
Provides-Extra: notebooks
Requires-Dist: pandas ; extra == 'notebooks'
Requires-Dist: jupyter ; extra == 'notebooks'
Requires-Dist: unicodecsv ; extra == 'notebooks'
Requires-Dist: bs4 ; extra == 'notebooks'
Requires-Dist: tqdm ; extra == 'notebooks'
Requires-Dist: regex ; extra == 'notebooks'
Requires-Dist: spacy ; extra == 'notebooks'
Provides-Extra: test
Requires-Dist: pytest ; extra == 'test'
Requires-Dist: tox ; extra == 'test'
